setup.cfg
setup.py
sitegen/__init__.py
sitegen/generate.py
sitegen.egg-info/PKG-INFO
sitegen.egg-info/SOURCES.txt
sitegen.egg-info/dependency_links.txt
sitegen.egg-info/entry_points.txt
sitegen.egg-info/not-zip-safe
sitegen.egg-info/requires.txt
sitegen.egg-info/top_level.txt