Metadata-Version: 1.0
Name: sitegen
Version: 0.9.2
Summary: Site Generator
Home-page: http://comlounge.net
Author: Christian Scholz
Author-email: cs@comlounge.net
License: MIT
Keywords: sitegenerator web html generation
Platform: UNKNOWN
